Metadata-Version: 1.1
Name: benchmark-django-rest-framework
Version: 1.0.0
Summary: A framework developing Django Rest API most efficiently.
Home-page: https://github.com/hqsh/benchmark-django-rest-framework
Author: Huang Qiangsheng
Author-email: hqsh@live.cn
License: UNKNOWN
Platform: UNKNOWN
Classifier: Development Status :: 5 - Production/Stable
Classifier: Environment :: Web Environment
Classifier: Intended Audience :: Developers
Classifier: Operating System :: OS Independent
Classifier: Programming Language :: Python
Classifier: Programming Language :: Python :: 2
Classifier: Programming Language :: Python :: 3
Classifier: Topic :: Software Development :: Libraries :: Python Modules
